galaxy/__init__.py
galaxy/http.py
galaxy/proc_tools.py
galaxy/reader.py
galaxy/registry_monitor.py
galaxy/task_manager.py
galaxy/tools.py
galaxy/api/__init__.py
galaxy/api/consts.py
galaxy/api/errors.py
galaxy/api/importer.py
galaxy/api/jsonrpc.py
galaxy/api/plugin.py
galaxy/api/types.py
galaxy/unittest/__init__.py
galaxy/unittest/mock.py
galaxy_plugin_api-0.70.dist-info/licenses/LICENSE
galaxy_plugin_api-0.70.dist-info/METADATA
galaxy_plugin_api-0.70.dist-info/WHEEL
galaxy_plugin_api-0.70.dist-info/top_level.txt
galaxy_plugin_api-0.70.dist-info/RECORD
