Metadata-Version: 2.4
Name: galaxy.plugin.api
Version: 0.70
Summary: GOG Galaxy Integrations Python API
Author: Galaxy team
Author-email: galaxy@gog.com
Requires-Python: ~=3.13.0
License-File: LICENSE
Requires-Dist: aiohttp>=3.12.15
Requires-Dist: certifi>=2025.8.3
Requires-Dist: psutil>=5.6.6; sys_platform == "darwin"
Dynamic: author
Dynamic: author-email
Dynamic: license-file
Dynamic: requires-dist
Dynamic: requires-python
Dynamic: summary
